[
    {
        "total_count": "119",
        "created_at": "2017-03-19T13:32:51Z",
        "closed_at": "2017-03-23T05:14:20Z",
        "body_text": 120,
        "id_pr": "MDExOlB1bGxSZXF1ZXN0MTExNDUwMDcy",
        "reviews": 1,
        "participants": "4",
        "files": "2"
    },
    {
        "total_count": "119",
        "created_at": "2018-01-30T22:21:06Z",
        "closed_at": "2018-02-04T21:16:06Z",
        "body_text": 0,
        "id_pr": "MDExOlB1bGxSZXF1ZXN0MTY2MTEzODI1",
        "reviews": 1,
        "participants": "2",
        "files": "1"
    },
    {
        "total_count": "119",
        "created_at": "2018-10-13T22:00:01Z",
        "closed_at": "2020-01-04T07:21:27Z",
        "body_text": 37,
        "id_pr": "MDExOlB1bGxSZXF1ZXN0MjIyNjc4NzI3",
        "reviews": 1,
        "participants": "3",
        "files": "1"
    },
    {
        "total_count": "119",
        "created_at": "2018-12-31T09:16:04Z",
        "closed_at": "2019-05-06T16:37:15Z",
        "body_text": 132,
        "id_pr": "MDExOlB1bGxSZXF1ZXN0MjQxNTQxODk5",
        "reviews": 3,
        "participants": "3",
        "files": "2"
    },
    {
        "total_count": "119",
        "created_at": "2019-02-01T00:42:06Z",
        "closed_at": "2020-01-18T09:17:55Z",
        "body_text": 283,
        "id_pr": "MDExOlB1bGxSZXF1ZXN0MjQ5NDUxNDI5",
        "reviews": 3,
        "participants": "6",
        "files": "11"
    },
    {
        "total_count": "119",
        "created_at": "2019-10-16T02:41:44Z",
        "closed_at": "2020-01-18T09:03:14Z",
        "body_text": 246,
        "id_pr": "MDExOlB1bGxSZXF1ZXN0MzI4NTQyNDk5",
        "reviews": 3,
        "participants": "6",
        "files": "3"
    },
    {
        "total_count": "119",
        "created_at": "2019-10-29T17:42:05Z",
        "closed_at": "2020-01-03T14:58:05Z",
        "body_text": 75,
        "id_pr": "MDExOlB1bGxSZXF1ZXN0MzMzNzcxNjUz",
        "reviews": 2,
        "participants": "4",
        "files": "2"
    },
    {
        "total_count": "119",
        "created_at": "2020-02-20T05:49:47Z",
        "closed_at": "2020-03-13T21:15:05Z",
        "body_text": 685,
        "id_pr": "MDExOlB1bGxSZXF1ZXN0Mzc3NTYzNDg2",
        "reviews": 1,
        "participants": "3",
        "files": "6"
    },
    {
        "total_count": "119",
        "created_at": "2020-05-23T23:53:49Z",
        "closed_at": "2021-01-09T09:29:41Z",
        "body_text": 698,
        "id_pr": "MDExOlB1bGxSZXF1ZXN0NDIyMzQxODU4",
        "reviews": 2,
        "participants": "4",
        "files": "2"
    },
    {
        "total_count": "119",
        "created_at": "2021-01-12T01:57:31Z",
        "closed_at": "2021-01-12T05:53:40Z",
        "body_text": 654,
        "id_pr": "MDExOlB1bGxSZXF1ZXN0NTUzMTM1MjU3",
        "reviews": 1,
        "participants": "3",
        "files": "1"
    }
]