[
    {
        "total_count": "308",
        "created_at": "2016-10-06T15:49:06Z",
        "closed_at": "2016-10-06T21:20:55Z",
        "body_text": 0,
        "id_pr": "MDExOlB1bGxSZXF1ZXN0ODgyODkzNDU=",
        "reviews": 1,
        "participants": "3",
        "files": "1"
    },
    {
        "total_count": "308",
        "created_at": "2017-01-06T05:01:41Z",
        "closed_at": "2017-01-07T18:18:30Z",
        "body_text": 0,
        "id_pr": "MDExOlB1bGxSZXF1ZXN0MTAwNDEwMzI5",
        "reviews": 1,
        "participants": "3",
        "files": "1"
    },
    {
        "total_count": "308",
        "created_at": "2017-03-11T11:10:48Z",
        "closed_at": "2017-08-23T10:08:21Z",
        "body_text": 29,
        "id_pr": "MDExOlB1bGxSZXF1ZXN0MTEwMjU2Mjc0",
        "reviews": 2,
        "participants": "4",
        "files": "1"
    },
    {
        "total_count": "308",
        "created_at": "2018-10-24T19:32:15Z",
        "closed_at": "2020-02-12T05:53:16Z",
        "body_text": 40,
        "id_pr": "MDExOlB1bGxSZXF1ZXN0MjI1NTIzNTgx",
        "reviews": 4,
        "participants": "2",
        "files": "1"
    },
    {
        "total_count": "308",
        "created_at": "2020-06-01T15:56:43Z",
        "closed_at": "2020-10-03T19:01:34Z",
        "body_text": 109,
        "id_pr": "MDExOlB1bGxSZXF1ZXN0NDI2MDcwMjg3",
        "reviews": 3,
        "participants": "5",
        "files": "1"
    },
    {
        "total_count": "308",
        "created_at": "2020-10-01T03:50:15Z",
        "closed_at": "2020-10-02T14:45:19Z",
        "body_text": 0,
        "id_pr": "MDExOlB1bGxSZXF1ZXN0NDk1OTI5MjEx",
        "reviews": 1,
        "participants": "4",
        "files": "1"
    },
    {
        "total_count": "308",
        "created_at": "2020-10-03T04:35:58Z",
        "closed_at": "2020-10-03T18:58:22Z",
        "body_text": 165,
        "id_pr": "MDExOlB1bGxSZXF1ZXN0NDk3MjEzMzc0",
        "reviews": 1,
        "participants": "3",
        "files": "1"
    },
    {
        "total_count": "308",
        "created_at": "2020-12-30T15:55:16Z",
        "closed_at": "2020-12-30T17:38:35Z",
        "body_text": 0,
        "id_pr": "MDExOlB1bGxSZXF1ZXN0NTQ2OTk3MDQw",
        "reviews": 1,
        "participants": "3",
        "files": "1"
    },
    {
        "total_count": "308",
        "created_at": "2021-02-15T21:39:09Z",
        "closed_at": "2021-02-16T02:05:50Z",
        "body_text": 0,
        "id_pr": "MDExOlB1bGxSZXF1ZXN0NTczODA0NDI1",
        "reviews": 1,
        "participants": "4",
        "files": "1"
    }
]